splitit_client/__init__.py
splitit_client/api_client.py
splitit_client/configuration.py
splitit_client/exceptions.py
splitit_client/model_utils.py
splitit_client/rest.py
splitit_client/api/__init__.py
splitit_client/api/installment_plan_api.py
splitit_client/apis/__init__.py
splitit_client/model/__init__.py
splitit_client/model/address_data.py
splitit_client/model/address_data_model.py
splitit_client/model/authorization_model.py
splitit_client/model/card_data.py
splitit_client/model/error.py
splitit_client/model/error_extended.py
splitit_client/model/error_extended_all_of.py
splitit_client/model/failed_response.py
splitit_client/model/failed_response_all_of.py
splitit_client/model/gw_authorization_status.py
splitit_client/model/identifier_contract.py
splitit_client/model/installment.py
splitit_client/model/installment_plan_cancel_response.py
splitit_client/model/installment_plan_create_request.py
splitit_client/model/installment_plan_get_response.py
splitit_client/model/installment_plan_get_response_all_of.py
splitit_client/model/installment_plan_model.py
splitit_client/model/installment_plan_model_all_of.py
splitit_client/model/installment_plan_refund_request.py
splitit_client/model/installment_plan_refund_response.py
splitit_client/model/installment_plan_refund_response_all_of.py
splitit_client/model/installment_plan_update_request.py
splitit_client/model/installment_plan_update_request_by_identifier.py
splitit_client/model/installment_plan_update_request_by_identifier_all_of.py
splitit_client/model/installment_plan_update_response.py
splitit_client/model/installment_plan_update_response_all_of.py
splitit_client/model/installment_status.py
splitit_client/model/links_data.py
splitit_client/model/payment_method_model.py
splitit_client/model/payment_method_type.py
splitit_client/model/plan_data_model.py
splitit_client/model/plan_error_response.py
splitit_client/model/plan_error_response_all_of.py
splitit_client/model/plan_status.py
splitit_python_sdk-1.0.0.dist-info/METADATA
splitit_python_sdk-1.0.0.dist-info/WHEEL
splitit_python_sdk-1.0.0.dist-info/top_level.txt
splitit_python_sdk-1.0.0.dist-info/RECORD
