Metadata-Version: 2.1
Name: splitit-python-sdk
Version: 1.0.0
Summary: splitit-web-api-v3
Home-page: https://github.com/konfig-dev/splitit-sdks/tree/main/python
Author: Konfig
Author-email: engineering@konfigthis.com
Keywords: Konfig,splitit-web-api-v3
Requires-Python: >=3.6
Requires-Dist: urllib3 (>=1.25.3)
Requires-Dist: python-dateutil
